test_evocraft_py/__init__.py
test_evocraft_py/cli.py
test_evocraft_py/minecraft_pb2.py
test_evocraft_py/minecraft_pb2_grpc.py
test_evocraft_py/test_evocraft_py.py
test_evocraft_py/data/eula.txt
test_evocraft_py/data/server.properties
test_evocraft_py/data/spongevanilla-1.12.2-7.3.0.jar
test_evocraft_py/data/mods/minecraft-rpc-0.0.5.jar
test_evocraft_py-0.1.7.dist-info/LICENSE
test_evocraft_py-0.1.7.dist-info/METADATA
test_evocraft_py-0.1.7.dist-info/WHEEL
test_evocraft_py-0.1.7.dist-info/entry_points.txt
test_evocraft_py-0.1.7.dist-info/top_level.txt
test_evocraft_py-0.1.7.dist-info/RECORD
