Metadata-Version: 2.1
Name: test-evocraft-py
Version: 0.1.7
Summary: Python client for Evocraft
Home-page: UNKNOWN
Author: Shyam Sudhakaran
Author-email: shyamsnair@protonmail.com
License: MIT
Platform: UNKNOWN
Classifier: Development Status :: 2 - Pre-Alpha
Classifier: License :: OSI Approved :: MIT License
Classifier: Programming Language :: Python :: 3.8
